flatland/__init__.py
flatland/__main__.py
flatland/exceptions.py
flatland/log.conf
flatland/makeframe.py
flatland/names.py
flatland/configuration/__init__.py
flatland/configuration/configDB.py
flatland/configuration/connector_type.yaml
flatland/configuration/diagram_type.yaml
flatland/configuration/frame.yaml
flatland/configuration/layout_specification.yaml
flatland/configuration/metadata.yaml
flatland/configuration/name_placement.yaml
flatland/configuration/notation.yaml
flatland/configuration/sheet.yaml
flatland/configuration/titleblock.yaml
flatland/connector_subsystem/__init__.py
flatland/connector_subsystem/anchored_leaf_stem.py
flatland/connector_subsystem/anchored_stem.py
flatland/connector_subsystem/anchored_tree_stem.py
flatland/connector_subsystem/bending_binary_connector.py
flatland/connector_subsystem/binary_connector.py
flatland/connector_subsystem/branch.py
flatland/connector_subsystem/connector.py
flatland/connector_subsystem/floating_binary_stem.py
flatland/connector_subsystem/floating_leaf_stem.py
flatland/connector_subsystem/floating_stem.py
flatland/connector_subsystem/grafted_branch.py
flatland/connector_subsystem/interpolated_branch.py
flatland/connector_subsystem/rut_branch.py
flatland/connector_subsystem/stem.py
flatland/connector_subsystem/straight_binary_connector.py
flatland/connector_subsystem/ternary_stem.py
flatland/connector_subsystem/tree_connector.py
flatland/connector_subsystem/trunk_stem.py
flatland/connector_subsystem/unary_connector.py
flatland/database/__init__.py
flatland/database/flatland_db.py
flatland/database/pop_connector_subsys.py
flatland/database/pop_layout_spec.py
flatland/database/pop_node_subsys.py
flatland/database/pop_sheet_subsys.py
flatland/database/relvars.py
flatland/database/instances/__init__.py
flatland/database/instances/connector_subsystem.py
flatland/database/instances/node_subsystem.py
flatland/database/instances/sheet_subsystem.py
flatland/datatypes/__init__.py
flatland/datatypes/command_interface.py
mi_flatland-2.0.15.dist-info/licenses/LICENSE
mi_flatland-2.0.15.dist-info/METADATA
mi_flatland-2.0.15.dist-info/WHEEL
mi_flatland-2.0.15.dist-info/entry_points.txt
mi_flatland-2.0.15.dist-info/top_level.txt
mi_flatland-2.0.15.dist-info/RECORD
