Metadata-Version: 2.4
Name: mi-flatland
Version: 2.0.15
Summary: Model text file + layout text file -> beautiful diagram
Author-email: Leon Starr <leon_starr@modelint.com>
License: MIT License
Project-URL: repository, https://github.com/modelint/flatland
Project-URL: documentation, https://github.com/modelint/flatland
Keywords: 2D,draw,graphics,canvas,mbse,xuml,xtuml,sysml
Classifier: License :: OSI Approved :: MIT License
Classifier: Programming Language :: Python
Classifier: Programming Language :: Python :: 3
Requires-Python: <3.13,>=3.11
License-File: LICENSE
Requires-Dist: mi-configurator>=0
Requires-Dist: mi-pyral>=0
Requires-Dist: mi-tabletqt>=0
Requires-Dist: mls-parser>=0
Requires-Dist: xcm-parser>=0
Requires-Dist: xsm-parser>=0
Requires-Dist: numpy~=2.2.2
Requires-Dist: tomli; python_version < "3.12"
Provides-Extra: build
Requires-Dist: build; extra == "build"
Requires-Dist: twine; extra == "build"
Provides-Extra: dev
Requires-Dist: bump2version; extra == "dev"
Requires-Dist: pytest; extra == "dev"
Dynamic: license-file
